{
  "ver": 1,
  "app": {
    "dir_triggers": "data/triggers",
    "dir_sessions": "data/sessions",
    "class": "ListenGroup"
  },
  "tasks": [
    {
      "enabled": true,
      "session": "14158156130",
      "plugins": [
        {
          "enabled": true,
          "event": "NewMessage",
          "class": "GroupMessageFilter",
          "group": "udalenka_chatik",
          "trigger": "test.txt"
        },
        {
          "class": "GroupMessageFilter",
          "group": "workinchicago",
          "trigger": "test.txt"
        },
        {
          "class": "GroupMessageFilter",
          "group": "vacancies_infobiz",
          "trigger": "test.txt"
        },
        {
          "class": "GroupMessageFilter",
          "group": "gilbertwil",
          "trigger": "test.txt"
        },
        {
          "class": "GroupMessageFilter",
          "group": "ukraina_eskort",
          "trigger": "test.txt"
        },
        {
          "class": "GroupMessageFilter",
          "group": "savannamlbb",
          "trigger": "test.txt"
        },
        {
          "class": "GroupMessageFilter",
          "group": "hashira_mlbb",
          "trigger": "test.txt"
        },
        {
          "class": "GroupMessageFilter",
          "group": "mt103202transfer",
          "trigger": "test.txt"
        },
        {
          "class": "GroupMessageFilter",
          "group": "lowzemgwlls",
          "trigger": "test.txt"
        },
        {
          "class": "GroupMessageFilter",
          "group": "Nash_miami",
          "trigger": "test.txt"
        },
        {
          "class": "GroupMessageFilter",
          "group": "rostov_rabotaet",
          "trigger": "test.txt"
        },
        {
          "class": "GroupMessageFilter",
          "group": "gryzovik",
          "trigger": "test.txt"
        },
        {
          "class": "GroupMessageFilter",
          "group": "freelaceworkchat",
          "trigger": "test.txt"
        },
        {
          "class": "GroupMessageFilter",
          "group": "detiorlando",
          "trigger": "test.txt"
        },
        {
          "class": "GroupMessageFilter",
          "group": "miami2020russian",
          "trigger": "test.txt"
        },
        {
          "class": "GroupMessageFilter",
          "group": "footbolteame",
          "trigger": "test.txt"
        },
        {
          "class": "GroupMessageFilter",
          "group": "tempesstgacor",
          "trigger": "test.txt"
        },
        {
          "class": "GroupMessageFilter",
          "group": "new_york_ru",
          "trigger": "test.txt"
        },
        {
          "class": "GroupMessageFilter",
          "group": "grandmobail_chat",
          "trigger": "test.txt"
        },
        {
          "class": "GroupMessageFilter",
          "group": "concentrat_voronezh",
          "trigger": "test.txt"
        },
        {
          "class": "GroupMessageFilter",
          "group": "chatskzry",
          "trigger": "test.txt"
        },
        {
          "class": "GroupMessageFilter",
          "group": "work_in_miami_florida",
          "trigger": "test.txt"
        },
        {
          "class": "GroupMessageFilter",
          "group": "unityservices",
          "trigger": "test.txt"
        },
        {
          "class": "GroupMessageFilter",
          "group": "perevozshik7777",
          "trigger": "test.txt"
        },
        {
          "class": "GroupMessageFilter",
          "group": "concentratcertain9",
          "trigger": "test.txt"
        }
      ]
    }
  ]
}